tidecv/__init__.py
tidecv/ap.py
tidecv/data.py
tidecv/functions.py
tidecv/plotting.py
tidecv/quantify.py
tidecv/errors/__init__.py
tidecv/errors/error.py
tidecv/errors/main_errors.py
tidecv/errors/qualifiers.py
tidecv_light-1.0.2.dist-info/LICENSE
tidecv_light-1.0.2.dist-info/METADATA
tidecv_light-1.0.2.dist-info/WHEEL
tidecv_light-1.0.2.dist-info/top_level.txt
tidecv_light-1.0.2.dist-info/RECORD
