Metadata-Version: 2.1
Name: tidecv-light
Version: 1.0.2
Summary: A General Toolbox for Identifying ObjectDetection Errors
Home-page: https://github.com/jpsimen/tide
Author: Daniel Bolya
Author-email: dbolya@gatech.edu
License: MIT
Classifier: License :: OSI Approved :: MIT License
Classifier: Programming Language :: Python :: 3
Classifier: Programming Language :: Python :: 3.6
Classifier: Operating System :: OS Independent
Requires-Python: >=3.6
License-File: LICENSE
Requires-Dist: numpy
